beevisionseo/__init__.py
beevisionseo/client.py
beevisionseo/config.py
beevisionseo/exceptions.py
beevisionseo/utils.py
beevisionseo-0.1.0.dist-info/METADATA
beevisionseo-0.1.0.dist-info/WHEEL
beevisionseo-0.1.0.dist-info/licenses/LICENSE
beevisionseo-0.1.0.dist-info/RECORD
