Metadata-Version: 2.4
Name: beevisionseo
Version: 0.1.0
Summary: BeeVision SEO API Client Library
Project-URL: Homepage, https://github.com/Digitalbee-Labs/bvs-api-python-client
Project-URL: Issues, https://github.com/Digitalbee-Labs/bvs-api-python-client/issues
Author-email: BeeVision SEO <kushan.e@digitalbeelabs.com>
License-Expression: MIT
License-File: LICENSE
Classifier: License :: OSI Approved :: MIT License
Classifier: Operating System :: OS Independent
Classifier: Programming Language :: Python :: 3
Requires-Python: >=3.8
